django_context_memory/__init__.py
django_context_memory/analyzer.py
django_context_memory/apps.py
django_context_memory/builder.py
django_context_memory/cli.py
django_context_memory/config.py
django_context_memory/doc_generator.py
django_context_memory/scanner.py
django_context_memory/urls.py
django_context_memory/utils.py
django_context_memory/views.py
django_context_memory/templates/django_context_memory/index.html
django_context_memory-1.0.4.dist-info/licenses/LICENSE
django_context_memory-1.0.4.dist-info/METADATA
django_context_memory-1.0.4.dist-info/WHEEL
django_context_memory-1.0.4.dist-info/entry_points.txt
django_context_memory-1.0.4.dist-info/top_level.txt
django_context_memory-1.0.4.dist-info/RECORD
