Metadata-Version: 2.4
Name: django-context-memory
Version: 1.0.4
Summary: Deep code intelligence for AI assistants working with Django projects
Home-page: https://github.com/GavinHolder/django-context-memory
Author: Gavin Holder
Author-email: Gavin Holder <mangleholder@gmail.com>
License: MIT
Project-URL: Homepage, https://github.com/yourusername/django-context-memory
Project-URL: Documentation, https://django-context-memory.readthedocs.io
Project-URL: Repository, https://github.com/yourusername/django-context-memory
Project-URL: Bug Tracker, https://github.com/yourusername/django-context-memory/issues
Keywords: django,ai,claude,code-intelligence,context,ast,analysis
Classifier: Development Status :: 4 - Beta
Classifier: Intended Audience :: Developers
Classifier: Framework :: Django
Classifier: License :: OSI Approved :: MIT License
Classifier: Programming Language :: Python :: 3
Classifier: Programming Language :: Python :: 3.8
Classifier: Programming Language :: Python :: 3.9
Classifier: Programming Language :: Python :: 3.10
Classifier: Programming Language :: Python :: 3.11
Classifier: Programming Language :: Python :: 3.12
Requires-Python: >=3.8
License-File: LICENSE
Provides-Extra: dev
Requires-Dist: pytest>=7.0; extra == "dev"
Requires-Dist: pytest-cov>=4.0; extra == "dev"
Requires-Dist: black>=23.0; extra == "dev"
Requires-Dist: flake8>=6.0; extra == "dev"
Requires-Dist: mypy>=1.0; extra == "dev"
Provides-Extra: django
Requires-Dist: Django>=3.2; extra == "django"
Dynamic: author
Dynamic: home-page
Dynamic: license-file
Dynamic: requires-python
